{
  "_id": "51c75f7bb6f26ba1cd00002f",
  "name": "Little Stars Universe",
  "category": "Kids"
}
{
  "_id": "5268abcd0ce20a8472000114",
  "name": "Pluto TV News",
  "category": "News + Opinion"
}
{
  "_id": "5417a212ff9fba68282fbf5e",
  "name": "GLORY Kickboxing",
  "category": "Sports"
}
{
  "_id": "5421f71da6af422839419cb3",
  "name": "CNN HEADLINES",
  "category": "News + Opinion"
}
{
  "_id": "545943f1c9f133a519bbac92",
  "name": "MST3K",
  "category": "Comedy"
}
{
  "_id": "5459795fc9f133a519bc0bef",
  "name": "Scripps News",
  "category": "News + Opinion"
}
{
  "_id": "54ff7ba69222cb1c2624c584",
  "name": "Bloomberg TV",
  "category": "News + Opinion"
}
{
  "_id": "554158e864526b29254ff105",
  "name": "FailArmy",
  "category": "Comedy"
}
{
  "_id": "55a6a3275616b6240c26f393",
  "name": "Shout! TV",
  "category": "Classic TV"
}
{
  "_id": "55b179af994403942f3061d6",
  "name": "Newsmax2",
  "category": "News + Opinion"
}
{
  "_id": "55b285cd2665de274553d66f",
  "name": "Sky News",
  "category": "News + Opinion"
}
{
  "_id": "5616f9c0ada51f8004c4b091",
  "name": "World Poker Tour",
  "category": "Sports"
}
{
  "_id": "56171fafada51f8004c4b40f",
  "name": "Forever Kids",
  "category": "Kids"
}
{
  "_id": "561c5b0dada51f8004c4d855",
  "name": "Classic Movies Channel",
  "category": "Movies"
}
{
  "_id": "561c5f613286e48904fb2677",
  "name": "IGN",
  "category": "Entertainment"
}
{
  "_id": "561d7d484dc7c8770484914a",
  "name": "Pluto TV Action",
  "category": "Movies"
}
{
  "_id": "56340779a738201b4ccfeac9",
  "name": "Pluto TV Sports",
  "category": "Sports"
}
{
  "_id": "5637d31f319573e26b64040b",
  "name": "Stand-Up TV",
  "category": "Comedy"
}
{
  "_id": "563a970aa1a1f7fe7c9daad7",
  "name": "Pluto TV Science",
  "category": "History + Science"
}
{
  "_id": "569546031a619b8f07ce6e25",
  "name": "Pluto TV Horror",
  "category": "Movies"
}
{
  "_id": "56b27f85ff3037045055037e",
  "name": "Pluto TV Animals",
  "category": "Animals + Nature"
}
{
  "_id": "580e87ff497c73ba2f321dd3",
  "name": "Funny AF",
  "category": "Comedy"
}
{
  "_id": "5812b0f2237a6ff45d16c3f9",
  "name": "Fight",
  "category": "Sports"
}
{
  "_id": "5812b3a4249444e05d09cc46",
  "name": "Pluto TV Cars",
  "category": "Reality"
}
{
  "_id": "5812b7d3249444e05d09cc49",
  "name": "Anime All Day",
  "category": "Anime"
}
{
  "_id": "5812bcc8237a6ff45d16c407",
  "name": "Spike Pluto TV",
  "category": "Reality"
}
{
  "_id": "5812bd9f249444e05d09cc4e",
  "name": "Naturescape",
  "category": "Animals + Nature"
}
{
  "_id": "5812be1c249444e05d09cc50",
  "name": "Pluto TV True Crime",
  "category": "True Crime"
}
{
  "_id": "5812bfbe4ced4f7b601b12e6",
  "name": "BUZZR",
  "category": "Game Shows"
}
{
  "_id": "5873fc21cad696fb37aa9054",
  "name": "Live Music",
  "category": "Entertainment"
}
{
  "_id": "5877ac8cb791f4eb4a140d81",
  "name": "Pluto TV Food",
  "category": "Home + Food"
}
{
  "_id": "5877acecb16bb1e042ee453f",
  "name": "Pluto TV Weddings",
  "category": "Reality"
}
{
  "_id": "588128d17d64bc0d0f385c34",
  "name": "Fear Factor",
  "category": "Competition Reality"
}
{
  "_id": "589aa03df9ba56a84197a560",
  "name": "Voyager Documentaries",
  "category": "History + Science"
}
{
  "_id": "58af4c093a41ca9d4ecabe96",
  "name": "Black Cinema",
  "category": "Movies"
}
{
  "_id": "58d947b9e420d8656ee101ab",
  "name": "RiffTrax",
  "category": "Comedy"
}
{
  "_id": "58e55b14ad8e9c364d55f717",
  "name": "Flicks of Fury",
  "category": "Movies"
}
{
  "_id": "591105034c1806b47438342c",
  "name": "The Asylum",
  "category": "Sci-Fi"
}
{
  "_id": "599375885ceaac3cabccbed7",
  "name": "Cats 24/7",
  "category": "Animals + Nature"
}
{
  "_id": "59b722526996084038c01e1b",
  "name": "TNA Wrestling",
  "category": "Sports"
}
{
  "_id": "59c01b1953680139c6ae9d4d",
  "name": "Pluto TV Travel",
  "category": "History + Science"
}
{
  "_id": "5a4d35dfa5c02e717a234f86",
  "name": "Pluto TV History",
  "category": "History + Science"
}
{
  "_id": "5a4d3a00ad95e4718ae8d8db",
  "name": "Pluto TV Comedy",
  "category": "Movies"
}
{
  "_id": "5a66795ef91fef2c7031c599",
  "name": "Pluto TV Romance",
  "category": "Movies"
}
{
  "_id": "5a6b92f6e22a617379789618",
  "name": "CBS News 24/7",
  "category": "News + Opinion"
}
{
  "_id": "5a74b8e1e22a61737979c6bf",
  "name": "FOX Sports",
  "category": "Sports"
}
{
  "_id": "5adf96e3e738977e2c31cb04",
  "name": "Pluto TV Paranormal",
  "category": "Reality"
}
{
  "_id": "5aea40b35126c2157123aa64",
  "name": "The New Detectives",
  "category": "True Crime"
}
{
  "_id": "5aec96ec5126c2157123c657",
  "name": "Nosey",
  "category": "Daytime TV"
}
{
  "_id": "5af09e645126c2157123f9eb",
  "name": "Kevin Hart’s LOL! Network",
  "category": "Comedy"
}
{
  "_id": "5b329e0a7b9d8872aeb49ceb",
  "name": "Dogs 24/7",
  "category": "Animals + Nature"
}
{
  "_id": "5b4e69e08291147bd04a9fd7",
  "name": "Pluto TV Thrillers",
  "category": "Movies"
}
{
  "_id": "5b4e92e4694c027be6ecece1",
  "name": "Pluto TV Drama",
  "category": "Movies"
}
{
  "_id": "5b4e94282d4ec87bdcbb87cd",
  "name": "Pluto TV Westerns",
  "category": "Movies"
}
{
  "_id": "5b4e96a0423e067bd6df6901",
  "name": "Unsolved Mysteries",
  "category": "True Crime"
}
{
  "_id": "5b4e99f4423e067bd6df6903",
  "name": "Gordon Ramsay's Hell's Kitchen",
  "category": "Competition Reality"
}
{
  "_id": "5b4fc274694c027be6ed3eea",
  "name": "Pluto TV Sci-Fi",
  "category": "Sci-Fi"
}
{
  "_id": "5b64a245a202b3337f09e51d",
  "name": "Pluto TV Fantastic",
  "category": "Movies"
}
{
  "_id": "5b68a18823ecb93393cba2f1",
  "name": "British Drama",
  "category": "Drama"
}
{
  "_id": "5b85a7582921777994caea63",
  "name": "Pluto TV Documentaries",
  "category": "Movies"
}
{
  "_id": "5ba3fb9c4b078e0f37ad34e8",
  "name": "Pluto TV Spotlight",
  "category": "Movies"
}
{
  "_id": "5bb1ad55268cae539bcedb08",
  "name": "The Pet Collective",
  "category": "Animals + Nature"
}
{
  "_id": "5bb1af6a268cae539bcedb0a",
  "name": "Forensic Files",
  "category": "True Crime"
}
{
  "_id": "5bb3fea0f711fd76340eebff",
  "name": "Pluto TV Military",
  "category": "History + Science"
}
{
  "_id": "5bdcdf1e851dd5632e2c11d1",
  "name": "QVC",
  "category": "Daytime TV"
}
{
  "_id": "5bee1a7359ee03633e780238",
  "name": "Dog the Bounty Hunter",
  "category": "Reality"
}
{
  "_id": "5c01df1759ee03633e7b272c",
  "name": "Lucha Libre AAA",
  "category": "En Español"
}
{
  "_id": "5c12ba66eae03059cbdc77f2",
  "name": "Pluto TV Cars",
  "category": "Reality"
}
{
  "_id": "5c2d64ffbdf11b71587184b8",
  "name": "TV Land Sitcoms",
  "category": "Comedy"
}
{
  "_id": "5c37d6712de254456f7ec340",
  "name": "Cold Case Files by A&E",
  "category": "True Crime"
}
{
  "_id": "5c393cad2de254456f7ef8c2",
  "name": "Spike Outdoors",
  "category": "Reality"
}
{
  "_id": "5c3f8f12a93c2d61b9990a4e",
  "name": "TokuSHOUTsu",
  "category": "Sci-Fi"
}
{
  "_id": "5c665db3e6c01b72c4977bc2",
  "name": "Pluto TV Cult Films",
  "category": "Movies"
}
{
  "_id": "5c6dc88fcd232425a6e0f06e",
  "name": "Pluto TV Terror",
  "category": "Movies"
}
{
  "_id": "5c6eeb85c05dfc257e5a50c4",
  "name": "Degrassi",
  "category": "Drama"
}
{
  "_id": "5ca525b650be2571e3943c63",
  "name": "80s Rewind",
  "category": "Movies"
}
{
  "_id": "5ca670f6593a5d78f0e85aed",
  "name": "BET Pluto TV",
  "category": "Entertainment"
}
{
  "_id": "5ca671f215a62078d2ec0abf",
  "name": "Comedy Central Pluto TV",
  "category": "Comedy"
}
{
  "_id": "5ca672f515a62078d2ec0ad2",
  "name": "MTV Pluto TV",
  "category": "Entertainment"
}
{
  "_id": "5ca673e0d0bd6c2689c94ce3",
  "name": "Nickelodeon Pluto TV",
  "category": "Kids"
}
{
  "_id": "5ca6748a37b88b269472dad9",
  "name": "Nick Jr. Pluto TV",
  "category": "Kids"
}
{
  "_id": "5ca6899a37b88b269472ea4b",
  "name": "MTV Dating",
  "category": "Reality"
}
{
  "_id": "5cabdf1437b88b26947346b2",
  "name": "Pluto TV Backcountry",
  "category": "Reality"
}
{
  "_id": "5cb0cae7a461406ffe3f5213",
  "name": "Paramount Movie Channel",
  "category": "Movies"
}
{
  "_id": "5cbf6a868a1bce4a3d52a5e9",
  "name": "Midsomer Murders",
  "category": "Drama"
}
{
  "_id": "5ce4475cd43850831ca91ce7",
  "name": "Doctor Who Classic",
  "category": "Sci-Fi"
}
{
  "_id": "5ce44810b421747ae467b7cd",
  "name": "Antiques Roadshow UK",
  "category": "Home + Food"
}
{
  "_id": "5ce5a8954311f992edbe1da2",
  "name": "Logo Pluto TV",
  "category": "Entertainment"
}
{
  "_id": "5ced7d5df64be98e07ed47b6",
  "name": "NFL Channel",
  "category": "Sports"
}
{
  "_id": "5cf0622da00ca1e2f6fac712",
  "name": "EstrellaTV",
  "category": "En Español"
}
{
  "_id": "5cf968040ab7d8f181e6a68b",
  "name": "Cine Premiere",
  "category": "En Español"
}
{
  "_id": "5cf96b1c4f1ca3f0629f4bf0",
  "name": "Séptimo arte",
  "category": "En Español"
}
{
  "_id": "5cf96b8f4f1ca3f0629f4bf1",
  "name": "Investiga",
  "category": "En Español"
}
{
  "_id": "5cf96cc422df39f1a338d165",
  "name": "Telemundo telenovelas clásicas",
  "category": "En Español"
}
{
  "_id": "5cf96d351652631e36d4331f",
  "name": "MTV en español",
  "category": "En Español"
}
{
  "_id": "5cf96dad1652631e36d43320",
  "name": "Comedy Central en español",
  "category": "En Español"
}
{
  "_id": "5d0c16d686454ead733d08f8",
  "name": "TOTALLY TURTLES",
  "category": "Kids"
}
{
  "_id": "5d14fb6c84dd37df3b4290c5",
  "name": "Dora TV",
  "category": "Kids"
}
{
  "_id": "5d14fc31252d35decbc4080b",
  "name": "Yo! MTV",
  "category": "Music Videos"
}
{
  "_id": "5d14fd1a252d35decbc4080c",
  "name": "MTV Biggest Pop",
  "category": "Music Videos"
}
{
  "_id": "5d14fdb8ca91eedee1633117",
  "name": "MTV Spankin' New",
  "category": "Music Videos"
}
{
  "_id": "5d2cb7ac552e3773bc48982e",
  "name": "WeatherNation",
  "category": "News + Opinion"
}
{
  "_id": "5d3609cd6a6c78d7672f2a81",
  "name": "MTV Flow Latino",
  "category": "Music Videos"
}
{
  "_id": "5d40855b3fb0855028c99b6f",
  "name": "Dallas Cowboys Cheerleaders",
  "category": "Competition Reality"
}
{
  "_id": "5d40bebc5e3d2750a2239d7e",
  "name": "TV Land Drama",
  "category": "Drama"
}
{
  "_id": "5d48678d34ceb37d3c458a55",
  "name": "Wild 'N Out",
  "category": "Comedy"
}
{
  "_id": "5d48685da7e9f476aa8a1888",
  "name": "The Challenge",
  "category": "Competition Reality"
}
{
  "_id": "5d486acc34ceb37d3c458a64",
  "name": "The First",
  "category": "News + Opinion"
}
{
  "_id": "5d486b2eeddd9576d66f9066",
  "name": "TBN",
  "category": "Home + Food"
}
{
  "_id": "5d51ddf0369acdb278dfb05e",
  "name": "Love & Hip Hop",
  "category": "Reality"
}
{
  "_id": "5d51e2bceca5b4b2c0e06c50",
  "name": "Black Ink Crew",
  "category": "Reality"
}
{
  "_id": "5d51e6949ab8e2b35bdcaa9f",
  "name": "BET Her",
  "category": "Entertainment"
}
{
  "_id": "5d51e791b7dba3b2ae990ab2",
  "name": "This Old House",
  "category": "Home + Food"
}
{
  "_id": "5d695f7db53adf96b78e7ce3",
  "name": "TODAY All Day",
  "category": "Daytime TV"
}
{
  "_id": "5d7154fa8326b6ce4ec31f2e",
  "name": "VH1 I Love Reality",
  "category": "Reality"
}
{
  "_id": "5d71561df6f2e6d0b6493bf5",
  "name": "VH1 Hip Hop Family",
  "category": "Reality"
}
{
  "_id": "5d815eb889bca2ce7b746fdd",
  "name": "Baywatch",
  "category": "Drama"
}
{
  "_id": "5d81607ab737153ea3c1c80e",
  "name": "The Addams Family",
  "category": "Classic TV"
}
{
  "_id": "5d8beeb39b5d5d5f8c672530",
  "name": "Pluto TV Lives",
  "category": "Reality"
}
{
  "_id": "5d8bf0b06d2d855ee15115e3",
  "name": "Pluto TV Reality",
  "category": "Reality"
}
{
  "_id": "5d8bf1472907815f66a866dd",
  "name": "Pluto TV Celebrity",
  "category": "Reality"
}
{
  "_id": "5d8d08395f39465da6fb3ec4",
  "name": "Nickelodeon en español",
  "category": "Kids"
}
{
  "_id": "5d8d0fbaa8742fa3093899da",
  "name": "Foodies",
  "category": "En Español"
}
{
  "_id": "5d8d11baeb31c5a43b77bf59",
  "name": "Spike ¡extremo!",
  "category": "En Español"
}
{
  "_id": "5d8d164d92e97a5e107638d2",
  "name": "Cine adrenalina",
  "category": "En Español"
}
{
  "_id": "5d8d180092e97a5e107638d3",
  "name": "Cine terror",
  "category": "En Español"
}
{
  "_id": "5d93b4d71754e6a4298d086e",
  "name": "Mi obsesión favorita",
  "category": "En Español"
}
{
  "_id": "5d93b635b43dd1a399b39eee",
  "name": "Vevo Pop",
  "category": "Music Videos"
}
{
  "_id": "5da0c85bd2c9c10009370984",
  "name": "Naruto",
  "category": "Anime"
}
{
  "_id": "5da0d64d0e8a62000964ebe4",
  "name": "Vevo Latino",
  "category": "Music Videos"
}
{
  "_id": "5da0d75e84830900098a1ea0",
  "name": "Vevo Country",
  "category": "Music Videos"
}
{
  "_id": "5da0d83f66c9700009b96d0e",
  "name": "Vevo R&B",
  "category": "Music Videos"
}
{
  "_id": "5dae084727c8af0009fe40a4",
  "name": "Tosh.0",
  "category": "Comedy"
}
{
  "_id": "5dae0a40e8ee0d000975e99b",
  "name": "pocket.watch",
  "category": "Kids"
}
{
  "_id": "5dae0b4841a7d0000938ddbd",
  "name": "Court TV",
  "category": "True Crime"
}
{
  "_id": "5db0ad56edc89300090d2ebb",
  "name": "Kids Movie Club",
  "category": "Kids"
}
{
  "_id": "5db0ae5af8797b00095c0794",
  "name": "No Parents Allowed",
  "category": "Kids"
}
{
  "_id": "5dc0c78281eddb0009a02d5e",
  "name": "ET",
  "category": "Entertainment"
}
{
  "_id": "5dc1cb279c91420009db261d",
  "name": "Home.Made.Nation",
  "category": "Home + Food"
}
{
  "_id": "5dc48170e280c80009a861ab",
  "name": "CBS News New York",
  "category": "Local News"
}
{
  "_id": "5dc481cda1d430000948a1b4",
  "name": "CBS News Los Angeles",
  "category": "Local News"
}
{
  "_id": "5dc9b8223687ff000936ed79",
  "name": "CBS News New York",
  "category": "News + Opinion"
}
{
  "_id": "5dc9b875e280c80009a8a44a",
  "name": "CBS News Los Angeles",
  "category": "News + Opinion"
}
{
  "_id": "5dcc42446750e200093b15e2",
  "name": "CMT Pluto TV",
  "category": "Entertainment"
}
{
  "_id": "5de94dacb394a300099fa22a",
  "name": "PGA TOUR",
  "category": "Sports"
}
{
  "_id": "5df975e2b27cf5000921c102",
  "name": "beIN SPORTS XTRA",
  "category": "Sports"
}
{
  "_id": "5df97894467dfa00091c873c",
  "name": "NBC News NOW",
  "category": "News + Opinion"
}
{
  "_id": "5e150a3d73fd3f00094f722f",
  "name": "MTV Flow Latino",
  "category": "Music"
}
{
  "_id": "5e1f7da4bc7d740009831259",
  "name": "America's Voice News",
  "category": "News + Opinion"
}
{
  "_id": "5e1f7e089f23700009d66303",
  "name": "COPS",
  "category": "Reality"
}
{
  "_id": "5e46fba0c43b0d00096e5ac1",
  "name": "Blaze Live",
  "category": "News + Opinion"
}
{
  "_id": "5e54187aae660e00093561d6",
  "name": "Game Show Central",
  "category": "Game Shows"
}
{
  "_id": "5e66968a70f34c0007d050be",
  "name": "MLB",
  "category": "Sports"
}
{
  "_id": "5e7cf6c7b156d500078c5f44",
  "name": "OAN Plus",
  "category": "News + Opinion"
}
{
  "_id": "5e82530945600e0007ca076c",
  "name": "All Reality by WE tv",
  "category": "Reality"
}
{
  "_id": "5e8254118601b80007b4b7ae",
  "name": "Stories by AMC",
  "category": "Drama"
}
{
  "_id": "5e82547b6b3df60007fec2b5",
  "name": "Slightly Off IFC",
  "category": "Comedy"
}
{
  "_id": "5e825550e758c700077b0aef",
  "name": "The Rifleman",
  "category": "Classic TV"
}
{
  "_id": "5e82bb378601b80007b4bd78",
  "name": "The Walking Dead en español",
  "category": "En Español"
}
{
  "_id": "5e84db2db3851800077c871e",
  "name": "Amantes del romance",
  "category": "En Español"
}
{
  "_id": "5e84dbf4a838b60007ffbba1",
  "name": "Novelas con la abuela",
  "category": "En Español"
}
{
  "_id": "5e84dc59026b9b000766f9a2",
  "name": "Badass novelas",
  "category": "En Español"
}
{
  "_id": "5e84f54a82f05300080e6746",
  "name": "America's Test Kitchen",
  "category": "Home + Food"
}
{
  "_id": "5e8df4bc16e34700077e77d3",
  "name": "Western TV",
  "category": "Classic TV"
}
{
  "_id": "5e94cd036cc69d0007e8a1ba",
  "name": "Crímenes imperfectos",
  "category": "En Español"
}
{
  "_id": "5e9debf8c881310007d7bde1",
  "name": "Deal or No Deal",
  "category": "Game Shows"
}
{
  "_id": "5e9decb953e157000752321c",
  "name": "Judge Nosey",
  "category": "Daytime TV"
}
{
  "_id": "5e9f2c05172a0f0007db4786",
  "name": "CBS Sports HQ",
  "category": "Sports"
}
{
  "_id": "5eac6b8efb7a6500070b5c9b",
  "name": "Announcement",
  "category": "Pluto TV"
}
{
  "_id": "5eac6bf103a57700073efcc5",
  "name": "Announcement",
  "category": "Pluto TV"
}
{
  "_id": "5eac6c5d2240d80007327f5a",
  "name": "Announcement",
  "category": "Pluto TV"
}
{
  "_id": "5eb1aeb2fd4b8a00076c2047",
  "name": "CBS News Chicago",
  "category": "Local News"
}
{
  "_id": "5eb1af2ad345340008fccd1e",
  "name": "CBS News Boston",
  "category": "Local News"
}
{
  "_id": "5eb1afb21486df0007abc57c",
  "name": "CBS News Bay Area",
  "category": "Local News"
}
{
  "_id": "5eb1b05ea168cc000767ba67",
  "name": "CBS News Philadelphia",
  "category": "Local News"
}
{
  "_id": "5eb1b0bf2240d8000732a09c",
  "name": "CBS News Minnesota",
  "category": "Local News"
}
{
  "_id": "5eb1b12146cba40007aa7e5d",
  "name": "CBS News Colorado",
  "category": "Local News"
}
{
  "_id": "5eb1b17aa5277e00083f6521",
  "name": "CBS News Pittsburgh",
  "category": "Local News"
}
{
  "_id": "5eb301b7395671000780d100",
  "name": "Little Baby Bum",
  "category": "Kids"
}
{
  "_id": "5ebc8688f3697d00072f7cf8",
  "name": "Bellator MMA",
  "category": "Sports"
}
{
  "_id": "5eceb0d4065c240007688ec6",
  "name": "CBS News Texas",
  "category": "Local News"
}
{
  "_id": "5ef3977e5d773400077de284",
  "name": "Three's Company",
  "category": "Classic TV"
}
{
  "_id": "5efb60a9e426140007c78e4b",
  "name": "Movies on Verizon",
  "category": "Movies"
}
{
  "_id": "5efb61e2a876670007ac2233",
  "name": "Real Life on Verizon",
  "category": "Reality"
}
{
  "_id": "5efbd29e4aa26700076c0d06",
  "name": "CSI",
  "category": "Drama"
}
{
  "_id": "5efbd39f8c4ce900075d7698",
  "name": "Star Trek",
  "category": "Sci-Fi"
}
{
  "_id": "5f15e281b0b8840007324b55",
  "name": "Pluto TV Suspense",
  "category": "Drama"
}
{
  "_id": "5f15e32b297f96000768f928",
  "name": "Classic TV Comedy",
  "category": "Classic TV"
}
{
  "_id": "5f15e3cccf49290007053c67",
  "name": "Classic TV Drama",
  "category": "Classic TV"
}
{
  "_id": "5f1efad04320070007dbb60b",
  "name": "theGrio",
  "category": "Entertainment"
}
{
  "_id": "5f21e7b24744c60007c1f6fc",
  "name": "Survivor",
  "category": "Competition Reality"
}
{
  "_id": "5f21e831e9fe730007706acb",
  "name": "Rescue 911",
  "category": "Reality"
}
{
  "_id": "5f21e8a6e2f12b000755afdb",
  "name": "The Amazing Race",
  "category": "Competition Reality"
}
{
  "_id": "5f21ea08007a49000762d349",
  "name": "Smithsonian Channel Selects",
  "category": "History + Science"
}
{
  "_id": "5f24662bebe0f0000767de32",
  "name": "Supernatural Drama",
  "category": "Drama"
}
{
  "_id": "5f31fd1b4c510e00071c3103",
  "name": "Pluto TV Crime Drama",
  "category": "Drama"
}
{
  "_id": "5f32f26bcd8aea00071240e5",
  "name": "Vevo '70s",
  "category": "Music Videos"
}
{
  "_id": "5f32f397795b750007706448",
  "name": "Vevo Reggaeton & Trap",
  "category": "Music Videos"
}
{
  "_id": "5f36d726234ce10007784f2a",
  "name": "The Bob Ross Channel",
  "category": "Classic TV"
}
{
  "_id": "5f4d83e0a382c00007bc02e7",
  "name": "90210",
  "category": "Drama"
}
{
  "_id": "5f4d8594eb979c0007706de7",
  "name": "Pluto TV Crime Movies",
  "category": "Movies"
}
{
  "_id": "5f4d863b98b41000076cd061",
  "name": "Pluto TV Staff Picks",
  "category": "Movies"
}
{
  "_id": "5f4d86f519358a00072b978e",
  "name": "90s Throwback",
  "category": "Movies"
}
{
  "_id": "5f4d878d3d19b30007d2e782",
  "name": "70s Cinema",
  "category": "Movies"
}
{
  "_id": "5f4d882d5233170007ee880e",
  "name": "Misterios sin resolver",
  "category": "En Español"
}
{
  "_id": "5f4ec10ed9636f00089b8c89",
  "name": "Yu-Gi-Oh!",
  "category": "Anime"
}
{
  "_id": "5f513564e4622a0007c578c0",
  "name": "Cine ¡¡jaja!!",
  "category": "En Español"
}
{
  "_id": "5f5136317aedfb0007016f93",
  "name": "Cine XOXO",
  "category": "En Español"
}
{
  "_id": "5f62dc3a71bc8b0007572fb0",
  "name": "Forensic Files 2",
  "category": "Pluto TV"
}
{
  "_id": "5f68f53eb1e5800007390bf8",
  "name": "CMT Equal Play",
  "category": "Music Videos"
}
{
  "_id": "5f778729ac60bd0007023d07",
  "name": "CSI 2",
  "category": "Pluto TV"
}
{
  "_id": "5f77879983bec60007e2a196",
  "name": "Star Trek 2",
  "category": "Pluto TV"
}
{
  "_id": "5f7787e802a7ee0007a08d20",
  "name": "Love & Hip Hop 2",
  "category": "Pluto TV"
}
{
  "_id": "5f77884314396a00070dfd5b",
  "name": "Unsolved Mysteries 2",
  "category": "Pluto TV"
}
{
  "_id": "5f7788ab8777280007781296",
  "name": "Nosey 2",
  "category": "Pluto TV"
}
{
  "_id": "5f77895fb3add2000735ac29",
  "name": "BET Pluto TV 3",
  "category": "Pluto TV"
}
{
  "_id": "5f7789c1d210fd0007a92182",
  "name": "VH1 Hip Hop Family 2",
  "category": "Pluto TV"
}
{
  "_id": "5f778a052360b30007fa5e32",
  "name": "TV Land Sitcoms 2",
  "category": "Pluto TV"
}
{
  "_id": "5f778a59b02eb40007f6d70b",
  "name": "Logo Pluto TV 2",
  "category": "Pluto TV"
}
{
  "_id": "5f7790b3ed0c88000720b241",
  "name": "One Piece",
  "category": "Anime"
}
{
  "_id": "5f7791b8372da90007fd45e6",
  "name": "The Price Is Right: The Barker Era",
  "category": "Game Shows"
}
{
  "_id": "5f77939a630f530007dde654",
  "name": "Family Ties",
  "category": "Classic TV"
}
{
  "_id": "5f7794162a4559000781fc12",
  "name": "Happy Days",
  "category": "Classic TV"
}
{
  "_id": "5f7794a788d29000079d2f07",
  "name": "The Love Boat",
  "category": "Classic TV"
}
{
  "_id": "5f7796e470510900070d4e3d",
  "name": "Beverly Hillbillies",
  "category": "Classic TV"
}
{
  "_id": "5f77977bd924d80007eee60c",
  "name": "Mission Impossible",
  "category": "Classic TV"
}
{
  "_id": "5f779951372da90007fd45e8",
  "name": "Classica",
  "category": "Music Videos"
}
{
  "_id": "5f8a02476b72230007e62b7d",
  "name": "HSN",
  "category": "Daytime TV"
}
{
  "_id": "5f99e24636d67d0007a94e6d",
  "name": "Comedy Central Animation",
  "category": "Comedy"
}
{
  "_id": "5fb5836fe745b600070fc743",
  "name": "BBC Home & Garden",
  "category": "Home + Food"
}
{
  "_id": "5fb5844bf5514d0007945bda",
  "name": "BBC Food",
  "category": "Home + Food"
}
{
  "_id": "5fb584b7613a31000789de5a",
  "name": "Ryan and Friends",
  "category": "Kids"
}
{
  "_id": "5fc54366b04b2300072e31af",
  "name": "PokerGo",
  "category": "Sports"
}
{
  "_id": "5fd7b8bf927e090007685853",
  "name": "Vevo '80s",
  "category": "Music Videos"
}
{
  "_id": "5fd7bb1f86d94a000796e2c2",
  "name": "Vevo '90s",
  "category": "Music Videos"
}
{
  "_id": "5fd7bca3e0a4ee0007a38e8c",
  "name": "Vevo 2K",
  "category": "Music Videos"
}
{
  "_id": "5ff8c708653d080007361b14",
  "name": "Paramount+ Picks",
  "category": "Entertainment"
}
{
  "_id": "5fff49cfb5cd4f0007c2b0dc",
  "name": "News 12 New York",
  "category": "Local News"
}
{
  "_id": "6000a5a9e767980007b497ca",
  "name": "Crime 360 by A&E",
  "category": "True Crime"
}
{
  "_id": "6000a6f4c3f8550008fc9b91",
  "name": "Xtreme Outdoor Presented by HISTORY",
  "category": "Reality"
}
{
  "_id": "6008ddf24ef92b00079d61cf",
  "name": "Movies for Gamers",
  "category": "Movies"
}
{
  "_id": "601a0342dcf4370007566891",
  "name": "Tiny House Nation",
  "category": "Home + Food"
}
{
  "_id": "6022bd17849c620007f43ae0",
  "name": "Pluto TV Home",
  "category": "Home + Food"
}
{
  "_id": "6036e6e7ac69c400072afca2",
  "name": "Hot Bench",
  "category": "Daytime TV"
}
{
  "_id": "6036e7c385749f00075dbd3b",
  "name": "Pluto TV Game Shows",
  "category": "Game Shows"
}
{
  "_id": "603fde9026ecbf0007752c2c",
  "name": "Pluto TV Competition",
  "category": "Competition Reality"
}
{
  "_id": "604928d54a4f730007ff76bc",
  "name": "CSI en Español",
  "category": "En Español"
}
{
  "_id": "60492a1e6361250007679665",
  "name": "Emergencia 911",
  "category": "En Español"
}
{
  "_id": "60492a9bbca75b0007b1bfd5",
  "name": "Mundo paranormal",
  "category": "En Español"
}
{
  "_id": "60492b2794116800073e32dc",
  "name": "Hell's Kitchen en español",
  "category": "En Español"
}
{
  "_id": "60492c67f4c48700075b5d37",
  "name": "Entre nosotras",
  "category": "En Español"
}
{
  "_id": "60492dcf1c9b6a00089f41df",
  "name": "Euronews",
  "category": "En Español"
}
{
  "_id": "60492e6d7f3f560007ab0f62",
  "name": "Estrella News",
  "category": "En Español"
}
{
  "_id": "60492ee6375a3900079a158c",
  "name": "Nosey escándalos",
  "category": "En Español"
}
{
  "_id": "60492fdd9989d30007ccd30a",
  "name": "beIN SPORTS XTRA en español",
  "category": "En Español"
}
{
  "_id": "60493283ffc52f000710edae",
  "name": "Bebecito Bum y sus amigos",
  "category": "Kids"
}
{
  "_id": "60511efd71ec430007f50d97",
  "name": "Mundo viajero",
  "category": "En Español"
}
{
  "_id": "6051201a0aa8a70007c24a2a",
  "name": "Mundo geek",
  "category": "En Español"
}
{
  "_id": "605e479d5b8229000763e697",
  "name": "Sony Canal Escape Perfecto",
  "category": "En Español"
}
{
  "_id": "606b5ee42b54a100079dd593",
  "name": "Julia Child",
  "category": "Home + Food"
}
{
  "_id": "60807fd5db701400078219c2",
  "name": "Ink Master",
  "category": "Competition Reality"
}
{
  "_id": "6089788de5c8410007808e26",
  "name": "Wanted: Dead or Alive",
  "category": "Classic TV"
}
{
  "_id": "609bfa51fbecc1000733152e",
  "name": "Jersey Shore",
  "category": "Reality"
}
{
  "_id": "60a3d889a5b3690008dc7fe8",
  "name": "Bar Rescue",
  "category": "Reality"
}
{
  "_id": "60c25ec6da6d6600074233a8",
  "name": "Acapulco Shore",
  "category": "En Español"
}
{
  "_id": "60cb6df2b2ad610008cd5bea",
  "name": "CBS News Sacramento",
  "category": "Local News"
}
{
  "_id": "60d39387706fe50007fda8e8",
  "name": "PBR RidePass",
  "category": "Sports"
}
{
  "_id": "60d393e5579a420007ee553c",
  "name": "Casos de la Dra. Polo",
  "category": "En Español"
}
{
  "_id": "60f5d389985a0c0007357304",
  "name": "BritBox Mysteries",
  "category": "Drama"
}
{
  "_id": "60f74ba51c82ac000776c669",
  "name": "Lupin the 3rd",
  "category": "Anime"
}
{
  "_id": "60f75178e7f8aa0007e9c259",
  "name": "The Andy Griffith Show",
  "category": "Classic TV"
}
{
  "_id": "60f754f98185580007eb0754",
  "name": "Matlock",
  "category": "Classic TV"
}
{
  "_id": "60f75771dfc72a00071fd0e0",
  "name": "Gunsmoke",
  "category": "Classic TV"
}
{
  "_id": "60f75919718aed0007250d7a",
  "name": "CBS News Baltimore",
  "category": "Local News"
}
{
  "_id": "60f760bbdf090700075d7bfe",
  "name": "Best of Dr. Phil",
  "category": "Daytime TV"
}
{
  "_id": "60f85644a9493e0007a1f035",
  "name": "Black Classics",
  "category": "Classic TV"
}
{
  "_id": "60f86f539f03cd00070c503a",
  "name": "Pluto TV Pranks",
  "category": "Comedy"
}
{
  "_id": "60f870184865da00074210ee",
  "name": "British Comedy",
  "category": "Comedy"
}
{
  "_id": "60f9ebb06f0b3d000746fbdb",
  "name": "Team Spirit",
  "category": "Kids"
}
{
  "_id": "60faf9368c7ad900082bc9a8",
  "name": "Find Out Why",
  "category": "Kids"
}
{
  "_id": "60faf9ddfcc1f200070a5932",
  "name": "Garfield and Friends",
  "category": "Kids"
}
{
  "_id": "60fafef7c2440500071266e0",
  "name": "Grande-ish",
  "category": "Kids"
}
{
  "_id": "60faffc3fbbc120007fc4376",
  "name": "Baby Shark TV",
  "category": "Kids"
}
{
  "_id": "60fb01a24795a6000762fe83",
  "name": "LEGO Kids TV",
  "category": "Kids"
}
{
  "_id": "60fb028c2e6a0c00075275a5",
  "name": "Rainbow Squad",
  "category": "Kids"
}
{
  "_id": "60fb040d4795a6000762fe8f",
  "name": "Kartoon Channel!",
  "category": "Kids"
}
{
  "_id": "60fb053712f22a0007ff14d2",
  "name": "Transformers TV",
  "category": "Kids"
}
{
  "_id": "60fb299b79498900070b29e0",
  "name": "CBS News Miami",
  "category": "Local News"
}
{
  "_id": "60fb2f47c133270007327375",
  "name": "Pelis y Popcorn",
  "category": "En Español"
}
{
  "_id": "60fb3087fbbc120007fc46be",
  "name": "Series con Ñ",
  "category": "En Español"
}
{
  "_id": "60fb321ee99fac0008c9ab8a",
  "name": "CBS News Spotlight",
  "category": "News + Opinion"
}
{
  "_id": "610c5f80f71f660007a2ad8e",
  "name": "Pluto TV Soaps",
  "category": "Daytime TV"
}
{
  "_id": "6127e12ed140e900077e7b6f",
  "name": "Teen Mom",
  "category": "Reality"
}
{
  "_id": "612fea0e970e6f00083be56b",
  "name": "TV Land Drama",
  "category": "Drama"
}
{
  "_id": "61325c4f982acd000723287e",
  "name": "Classic TV Crime Drama",
  "category": "Classic TV"
}
{
  "_id": "61325d18f5166c00081b84e0",
  "name": "Classic TV: Families",
  "category": "Classic TV"
}
{
  "_id": "613260e4bdb71c00070d63fa",
  "name": "More TV Drama",
  "category": "Drama"
}
{
  "_id": "6132619f9ddaa50007e7dd86",
  "name": "More TV Sitcoms",
  "category": "Comedy"
}
{
  "_id": "61326275b3c86a00078e4833",
  "name": "Black Throwbacks",
  "category": "Comedy"
}
{
  "_id": "6139497b7b47730007e81cdd",
  "name": "Announcement",
  "category": "Pluto TV"
}
{
  "_id": "6148c756ce8091000748d113",
  "name": "Iron Chef",
  "category": "Competition Reality"
}
{
  "_id": "615b8ec39e878900073f419a",
  "name": "Antiques Road Trip",
  "category": "Home + Food"
}
{
  "_id": "6176f39e709f160007ec61c3",
  "name": "48 Hours",
  "category": "True Crime"
}
{
  "_id": "6176fd25e83a5f0007a464c9",
  "name": "Bounce XL",
  "category": "Entertainment"
}
{
  "_id": "6176fddda3a6160007f60433",
  "name": "Shades of Black",
  "category": "Entertainment"
}
{
  "_id": "6176ff3ba00900000763710f",
  "name": "K-Content by CJ ENM",
  "category": "Entertainment"
}
{
  "_id": "617b37b361e0fd0008cfd8c5",
  "name": "Pluto TV Reaction",
  "category": "Movies"
}
{
  "_id": "61858ac0491af10007f8ce4f",
  "name": "Best of The Drew Barrymore Show",
  "category": "Daytime TV"
}
{
  "_id": "6197086891ddd4000739941a",
  "name": "Perry Mason",
  "category": "Classic TV"
}
{
  "_id": "61b3b8c645b45d0007a9bb8d",
  "name": "Blue Bloods",
  "category": "Drama"
}
{
  "_id": "61b3e21d56fee300087e4cba",
  "name": "Corazón turco",
  "category": "En Español"
}
{
  "_id": "61d4b38226b8a50007fe03a6",
  "name": "Vevo Retro Rock",
  "category": "Music Videos"
}
{
  "_id": "61d4c2817a823d00070ba53e",
  "name": "Vevo True School Hip-Hop",
  "category": "Music Videos"
}
{
  "_id": "61f07513227feb00073ee6bc",
  "name": "Heartland",
  "category": "Drama"
}
{
  "_id": "620bfa7df72827000703ddb1",
  "name": "Stargate",
  "category": "Sci-Fi"
}
{
  "_id": "623a1b5188ecdc0007c9ef5a",
  "name": "XITE Rock",
  "category": "Music Videos"
}
{
  "_id": "623b92a2ccefed0007b1db48",
  "name": "XITE Classic Country",
  "category": "Music Videos"
}
{
  "_id": "623b93628e6ded0007337d4d",
  "name": "XITE Gospel",
  "category": "Music Videos"
}
{
  "_id": "6267352efcf21c0007c76642",
  "name": "Let's Make A Deal",
  "category": "Game Shows"
}
{
  "_id": "627ae4fcf001df00074d6e5b",
  "name": "The Weather Channel En Español",
  "category": "En Español"
}
{
  "_id": "6283d51144ad8f0007fa382d",
  "name": "The Judge Judy Channel",
  "category": "Daytime TV"
}
{
  "_id": "628c274a02000400070a3ae4",
  "name": "WeatherNation Raleigh-Durham",
  "category": "News + Opinion"
}
{
  "_id": "628e685ba3811100070551a8",
  "name": "Hallmark Movies & More",
  "category": "Entertainment"
}
{
  "_id": "62ba60f059624e000781c436",
  "name": "00s Replay",
  "category": "Movies"
}
{
  "_id": "62cdc75b1a1cbd0007ed45dc",
  "name": "CBS News Chicago",
  "category": "News + Opinion"
}
{
  "_id": "62cdca1cda044a00077b903d",
  "name": "CBS News Philadelphia",
  "category": "News + Opinion"
}
{
  "_id": "62f54c11b3af68000702c304",
  "name": "CSI: Miami",
  "category": "Drama"
}
{
  "_id": "62f54c6439183b000769fb8f",
  "name": "CSI: NY",
  "category": "Drama"
}
{
  "_id": "62fa8176b9884200074ef5ae",
  "name": "The Walking Dead Universe",
  "category": "Drama"
}
{
  "_id": "62fa81ccd1a7e90007c1ada0",
  "name": "AMC en español",
  "category": "En Español"
}
{
  "_id": "632b5950b515b000079e6b81",
  "name": "CSI: Miami en español",
  "category": "En Español"
}
{
  "_id": "632b606e12a67b0007c9e371",
  "name": "CSI: NY en español",
  "category": "En Español"
}
{
  "_id": "632b6233822bbc000748fd81",
  "name": "WFTV Orlando",
  "category": "Local News"
}
{
  "_id": "632b642933a6280007aaf265",
  "name": "WSB Atlanta",
  "category": "Local News"
}
{
  "_id": "632b648c08cd050007d94114",
  "name": "WSOC Charlotte",
  "category": "Local News"
}
{
  "_id": "633354b63df9700007f6a1b7",
  "name": "Sitcom Legends",
  "category": "Comedy"
}
{
  "_id": "63335b193583440007c859fb",
  "name": "Movie Favorites By Lifetime",
  "category": "Entertainment"
}
{
  "_id": "63335df531a7590007c226b9",
  "name": "Pluto TV Christmas",
  "category": "Entertainment"
}
{
  "_id": "6334a574605f140007e233c4",
  "name": "PFL MMA",
  "category": "Sports"
}
{
  "_id": "634dacf51d90320007fcd5fa",
  "name": "Star Trek Voyager",
  "category": "Sci-Fi"
}
{
  "_id": "634ee8f95aa9870007248333",
  "name": "Confess by Nosey",
  "category": "Daytime TV"
}
{
  "_id": "634f2610d5023700078f7dee",
  "name": "CBS News Detroit",
  "category": "Local News"
}
{
  "_id": "634f3011f4fff20007431641",
  "name": "I Love Lucy",
  "category": "Classic TV"
}
{
  "_id": "634f307c7a068e00072c9982",
  "name": "Rawhide",
  "category": "Classic TV"
}
{
  "_id": "636adc255bcf470007d6e0e2",
  "name": "Top Gear",
  "category": "Reality"
}
{
  "_id": "636c2b3c55d2e700074105c4",
  "name": "PBS Antiques Roadshow",
  "category": "Home + Food"
}
{
  "_id": "637413d8531e0c0007442d6d",
  "name": "Dateline 24/7",
  "category": "True Crime"
}
{
  "_id": "6375236f8573640007802129",
  "name": "AspireTV Life",
  "category": "Home + Food"
}
{
  "_id": "637e55347427a40007fac703",
  "name": "Sailor Moon",
  "category": "Anime"
}
{
  "_id": "63a0e33a45264d000850ed7e",
  "name": "Golazo Network",
  "category": "Sports"
}
{
  "_id": "63b48016d9dd51000828fa37",
  "name": "POWERNATION",
  "category": "Sports"
}
{
  "_id": "6400f731d200410008f9b339",
  "name": "MotorTrend FAST TV",
  "category": "Sports"
}
{
  "_id": "640a64bd73e013000893d4e0",
  "name": "PBS Nature",
  "category": "Animals + Nature"
}
{
  "_id": "64387bb1af2bd90008978a2b",
  "name": "Hollywood Squares",
  "category": "Game Shows"
}
{
  "_id": "64387c25e0789d000849f62e",
  "name": "More TV Game Shows",
  "category": "Game Shows"
}
{
  "_id": "643f035d5a0cd50008361534",
  "name": "The Price Is Right",
  "category": "Game Shows"
}
{
  "_id": "643f03b9d8436e0008edf021",
  "name": "Family Feud Classic",
  "category": "Game Shows"
}
{
  "_id": "6450209d939a5900084dba1d",
  "name": "Totally Teen",
  "category": "Kids"
}
{
  "_id": "6452c77ed3fdde00080eb3a8",
  "name": "Zoom! Zoom!",
  "category": "Kids"
}
{
  "_id": "6452c814939a590008567a3b",
  "name": "90's Kids",
  "category": "Kids"
}
{
  "_id": "6452c879e94c380008f6eb16",
  "name": "OUTtv Proud",
  "category": "Entertainment"
}
{
  "_id": "6452c8cee1979c0008608e27",
  "name": "Godzilla",
  "category": "Sci-Fi"
}
{
  "_id": "645e7828e1979c00087b75b4",
  "name": "MovieSphere by Lionsgate",
  "category": "Movies"
}
{
  "_id": "649b6898f2ec0000081a9460",
  "name": "DAZN Ringside",
  "category": "Sports"
}
{
  "_id": "649ddbfb6f29ec000874ca9e",
  "name": "Supermarket Sweep",
  "category": "Game Shows"
}
{
  "_id": "64b585f84ea480000838e446",
  "name": "Pluto TV Icons",
  "category": "Movies"
}
{
  "_id": "64b9671cdac71b0008f371df",
  "name": "Cine Clásico",
  "category": "En Español"
}
{
  "_id": "64d1606b4c5ed80008e3b8b9",
  "name": "Dynasty",
  "category": "Classic TV"
}
{
  "_id": "64d160f53c785e0008df525e",
  "name": "Top Rank Classics",
  "category": "Sports"
}
{
  "_id": "64d161c93c785e0008df575e",
  "name": "Vevo Íconos Latinos",
  "category": "En Español"
}
{
  "_id": "64d1867c6b1fdb0008c6c95b",
  "name": "Classic TV Variety",
  "category": "Classic TV"
}
{
  "_id": "64d2b6bf9b414d0008187d83",
  "name": "Real Disaster Channel",
  "category": "Reality"
}
{
  "_id": "64dab5fe35425100080e2991",
  "name": "Vevo Regional Mexicano",
  "category": "En Español"
}
{
  "_id": "64dab9df3d48f40008868091",
  "name": "The Jamie Oliver Channel",
  "category": "Home + Food"
}
{
  "_id": "64e561a4354251000823a0e0",
  "name": "Ghost Hunters",
  "category": "Reality"
}
{
  "_id": "65033c4b98020f0008547124",
  "name": "Action Drama",
  "category": "Drama"
}
{
  "_id": "6508be683a0d700008c534e4",
  "name": "ABC News Live",
  "category": "News + Opinion"
}
{
  "_id": "650b68bc2ce8e40008ac9c14",
  "name": "FanDuel TV Extra",
  "category": "Sports"
}
{
  "_id": "650b69cfd1f20c0008586bac",
  "name": "EarthDay 365",
  "category": "Animals + Nature"
}
{
  "_id": "650b6a0c6625510008e1043b",
  "name": "The Jack Hanna Channel",
  "category": "Animals + Nature"
}
{
  "_id": "651f239d9c7aeb0008286823",
  "name": "Dating Disasters",
  "category": "Reality"
}
{
  "_id": "65244c403fd33c0008ffff31",
  "name": "Car Chase",
  "category": "Reality"
}
{
  "_id": "6532e6a9bdf3cf000887ab29",
  "name": "More True Crime",
  "category": "True Crime"
}
{
  "_id": "6532e7b290a74c00084a3bb6",
  "name": "Hallmark en español",
  "category": "En Español"
}
{
  "_id": "6532e7fa045c3d0008514ca7",
  "name": "Warner Bros. TV Sweet Escapes",
  "category": "Home + Food"
}
{
  "_id": "6532e8342cf13100083b404c",
  "name": "Warner Bros. TV Say Yes to the Dress",
  "category": "Reality"
}
{
  "_id": "65453f30085df200085883d8",
  "name": "ION",
  "category": "Entertainment"
}
{
  "_id": "65492fc7056b9700088560b5",
  "name": "American Crimes",
  "category": "True Crime"
}
{
  "_id": "65493029ab052400089e9d2f",
  "name": "GolfPass",
  "category": "Sports"
}
{
  "_id": "6549306c83595c000815a696",
  "name": "NBC Sports",
  "category": "Sports"
}
{
  "_id": "654930a8346f420008d3b0b8",
  "name": "Oxygen True Crime Archives",
  "category": "True Crime"
}
{
  "_id": "6549310a53fc97000838fcc9",
  "name": "Bravo Vault",
  "category": "Reality"
}
{
  "_id": "6549316d2c1d330008631496",
  "name": "Real Housewives Vault",
  "category": "Reality"
}
{
  "_id": "654931d753fc97000838fe55",
  "name": "Top Chef Vault",
  "category": "Competition Reality"
}
{
  "_id": "6549322e53fc97000838febc",
  "name": "Million Dollar Listing Vault",
  "category": "Reality"
}
{
  "_id": "654932fa4d6d8f00084c4723",
  "name": "Bad Girls Club",
  "category": "Reality"
}
{
  "_id": "6549337183595c000815ad05",
  "name": "Murder, She Wrote",
  "category": "Classic TV"
}
{
  "_id": "654933ac986ad20008a1f406",
  "name": "Little House on the Prairie",
  "category": "Classic TV"
}
{
  "_id": "654933e253fc970008390114",
  "name": "Universal Action",
  "category": "Drama"
}
{
  "_id": "6549341853fc9700083901ac",
  "name": "Universal Crime",
  "category": "Classic TV"
}
{
  "_id": "65652f7fc0fc88000883537a",
  "name": "Crunchyroll",
  "category": "Anime"
}
{
  "_id": "656535fc2c46f30008870fae",
  "name": "BBC Earth",
  "category": "Animals + Nature"
}
{
  "_id": "65653817c917a5000844bc30",
  "name": "Criminal Minds",
  "category": "Drama"
}
{
  "_id": "656538bb635c3c0008695660",
  "name": "Perform by Lifetime",
  "category": "Reality"
}
{
  "_id": "656538f8954b020008d389db",
  "name": "UnXplained Zone",
  "category": "Reality"
}
{
  "_id": "6565413e4261ca0008215320",
  "name": "Pickers & Pawn",
  "category": "Reality"
}
{
  "_id": "65654230c917a5000844ce96",
  "name": "Home Crashers",
  "category": "Home + Food"
}
{
  "_id": "656542ae4261ca00082154a8",
  "name": "Ultimate Builds",
  "category": "Home + Food"
}
{
  "_id": "6565430c9d5ac4000822f508",
  "name": "Rustic Retreats",
  "category": "Home + Food"
}
{
  "_id": "6565436c9d5ac4000822f552",
  "name": "Medical Incredible",
  "category": "Reality"
}
{
  "_id": "65775a88b3801200084a39ed",
  "name": "StarTalk TV",
  "category": "History + Science"
}
{
  "_id": "65775af3b3801200084a3aa4",
  "name": "Feel Good Drama",
  "category": "Drama"
}
{
  "_id": "65775d29dfed030008cb3db2",
  "name": "Modern Marvels Presented by HISTORY",
  "category": "History + Science"
}
{
  "_id": "65775e07dfed030008cb3f47",
  "name": "4UV",
  "category": "Entertainment"
}
{
  "_id": "65a6d85c3af63d0008278675",
  "name": "Love & Hip Hop",
  "category": "The Black Collective"
}
{
  "_id": "65a6d8e13af63d0008278715",
  "name": "Vevo R&B",
  "category": "The Black Collective"
}
{
  "_id": "65a6d90d3af63d0008278747",
  "name": "XITE Gospel",
  "category": "The Black Collective"
}
{
  "_id": "65a6dafb7bdc8d0008473c85",
  "name": "The Lone Ranger",
  "category": "Classic TV"
}
{
  "_id": "65a9b20f0c7ff50008d3a3b6",
  "name": "Universal Monsters",
  "category": "Movies"
}
{
  "_id": "65c69b683ba51e00084534a3",
  "name": "Monster Jam",
  "category": "Sports"
}
{
  "_id": "65c69bbfd77d450008c7ffee",
  "name": "Star Trek Deep Space Nine",
  "category": "Sci-Fi"
}
{
  "_id": "65c69bf23ef47d0008583967",
  "name": "Tough Jobs",
  "category": "Reality"
}
{
  "_id": "65c69ee3d77d450008c80438",
  "name": "Formula 1 Channel",
  "category": "Sports"
}
{
  "_id": "65ca98dc3a116800079c268a",
  "name": "Anime on Verizon",
  "category": "Anime"
}
{
  "_id": "65d92a8c8b24c80008e285c0",
  "name": "BBC News",
  "category": "News + Opinion"
}
{
  "_id": "65e23f340d4561000821540d",
  "name": "Mister Rogers' Neighborhood",
  "category": "Kids"
}
{
  "_id": "65ea8b928145cb0008509426",
  "name": "UEFA Champions League",
  "category": "Sports"
}
{
  "_id": "661827ffe8fba800086b217d",
  "name": "Triton Poker",
  "category": "Sports"
}
{
  "_id": "663946c1b18d700008d9c168",
  "name": "Black Visionaries",
  "category": "Movies"
}
{
  "_id": "663d24a7cb3ea10008f567d3",
  "name": "Live Music",
  "category": "The Black Collective"
}
{
  "_id": "663d36fa41af640008c083f6",
  "name": "Vevo True School Hip-Hop",
  "category": "The Black Collective"
}
{
  "_id": "66439ee041af640008ccaa98",
  "name": "Black Visionaries",
  "category": "The Black Collective"
}
